treen/__init__.py
treewe/__init__.py
treewe/utils.py
treewe-0.0.1.dist-info/METADATA
treewe-0.0.1.dist-info/WHEEL
treewe-0.0.1.dist-info/top_level.txt
treewe-0.0.1.dist-info/RECORD
