Metadata-Version: 2.1
Name: treewe
Version: 0.0.1
Summary: A Python library for energy prediction using decision trees.
Author: rebase.energy
Requires-Python: >=3.7
Requires-Dist: enerflow >=0.0.1
Requires-Dist: shap >=0.39.0
Requires-Dist: lightgbm >=3.3.0
Requires-Dist: xgboost >=1.5.0
Requires-Dist: catboost >=0.26
Requires-Dist: pandas >=1.0.0
Requires-Dist: numpy >=1.19.0
Requires-Dist: scikit-learn >=0.24.0
